dbos-2.7.0.dist-info/METADATA
dbos-2.7.0.dist-info/WHEEL
dbos-2.7.0.dist-info/entry_points.txt
dbos-2.7.0.dist-info/licenses/LICENSE
dbos/__init__.py
dbos/__main__.py
dbos/_admin_server.py
dbos/_app_db.py
dbos/_classproperty.py
dbos/_client.py
dbos/_conductor/conductor.py
dbos/_conductor/protocol.py
dbos/_context.py
dbos/_core.py
dbos/_croniter.py
dbos/_dbos.py
dbos/_dbos_config.py
dbos/_debouncer.py
dbos/_debug.py
dbos/_docker_pg_helper.py
dbos/_error.py
dbos/_event_loop.py
dbos/_fastapi.py
dbos/_flask.py
dbos/_kafka.py
dbos/_kafka_message.py
dbos/_logger.py
dbos/_migration.py
dbos/_outcome.py
dbos/_queue.py
dbos/_recovery.py
dbos/_registrations.py
dbos/_roles.py
dbos/_scheduler.py
dbos/_schemas/__init__.py
dbos/_schemas/application_database.py
dbos/_schemas/system_database.py
dbos/_serialization.py
dbos/_sys_db.py
dbos/_sys_db_postgres.py
dbos/_sys_db_sqlite.py
dbos/_templates/dbos-db-starter/README.md
dbos/_templates/dbos-db-starter/__package/__init__.py
dbos/_templates/dbos-db-starter/__package/main.py.dbos
dbos/_templates/dbos-db-starter/__package/schema.py
dbos/_templates/dbos-db-starter/dbos-config.yaml.dbos
dbos/_templates/dbos-db-starter/migrations/create_table.py.dbos
dbos/_templates/dbos-db-starter/start_postgres_docker.py
dbos/_tracer.py
dbos/_utils.py
dbos/_workflow_commands.py
dbos/cli/_github_init.py
dbos/cli/_template_init.py
dbos/cli/cli.py
dbos/cli/migration.py
dbos/dbos-config.schema.json
dbos/py.typed
version/__init__.py
dbos-2.7.0.dist-info/RECORD
