Metadata-Version: 2.1
Name: dbos
Version: 2.7.0
Summary: Ultra-lightweight durable execution in Python
Author-Email: "DBOS, Inc." <contact@dbos.dev>
License: MIT
Classifier: Development Status :: 5 - Production/Stable
Classifier: Programming Language :: Python
Classifier: Programming Language :: Python :: 3
Classifier: Programming Language :: Python :: 3 :: Only
Classifier: Programming Language :: Python :: 3.10
Classifier: Programming Language :: Python :: 3.11
Classifier: Programming Language :: Python :: 3.12
Classifier: Programming Language :: Python :: 3.13
Classifier: Intended Audience :: Developers
Classifier: Intended Audience :: Information Technology
Classifier: License :: OSI Approved :: MIT License
Classifier: Operating System :: OS Independent
Classifier: Topic :: Internet
Classifier: Topic :: Scientific/Engineering :: Artificial Intelligence
Classifier: Topic :: Database
Classifier: Topic :: Software Development :: Libraries :: Python Modules
Classifier: Framework :: AsyncIO
Requires-Python: >=3.10
Requires-Dist: pyyaml>=6.0.2
Requires-Dist: python-dateutil>=2.9.0.post0
Requires-Dist: psycopg[binary]>=3.1
Requires-Dist: websockets>=14.0
Requires-Dist: typer-slim>=0.17.4
Requires-Dist: sqlalchemy>=2.0.43
Provides-Extra: otel
Requires-Dist: opentelemetry-api>=1.37.0; extra == "otel"
Requires-Dist: opentelemetry-sdk>=1.37.0; extra == "otel"
Requires-Dist: opentelemetry-exporter-otlp-proto-http>=1.37.0; extra == "otel"
